{
  "dist_version": "0.31.0",
  "announcement_tag": "v0.4.5",
  "announcement_tag_is_implicit": false,
  "announcement_is_prerelease": false,
  "announcement_title": "v0.4.5",
  "announcement_github_body": "## Install moove 0.4.5\n\n### Install prebuilt binaries via Homebrew\n\n```sh\nbrew install urin/moove/moove\n```\n\n## Download moove 0.4.5\n\n|  File  | Platform | Checksum |\n|--------|----------|----------|\n| [moove-aarch64-apple-darwin.tar.gz](https://github.com/urin/moove/releases/download/v0.4.5/moove-aarch64-apple-darwin.tar.gz) | Apple Silicon macOS | [checksum](https://github.com/urin/moove/releases/download/v0.4.5/moove-aarch64-apple-darwin.tar.gz.sha256) |\n| [moove-x86_64-pc-windows-msvc.zip](https://github.com/urin/moove/releases/download/v0.4.5/moove-x86_64-pc-windows-msvc.zip) | x64 Windows | [checksum](https://github.com/urin/moove/releases/download/v0.4.5/moove-x86_64-pc-windows-msvc.zip.sha256) |\n| [moove-aarch64-unknown-linux-musl.tar.gz](https://github.com/urin/moove/releases/download/v0.4.5/moove-aarch64-unknown-linux-musl.tar.gz) | ARM64 MUSL Linux | [checksum](https://github.com/urin/moove/releases/download/v0.4.5/moove-aarch64-unknown-linux-musl.tar.gz.sha256) |\n| [moove-x86_64-unknown-linux-musl.tar.gz](https://github.com/urin/moove/releases/download/v0.4.5/moove-x86_64-unknown-linux-musl.tar.gz) | x64 MUSL Linux | [checksum](https://github.com/urin/moove/releases/download/v0.4.5/moove-x86_64-unknown-linux-musl.tar.gz.sha256) |\n\n## Verifying GitHub Artifact Attestations\n\nThe artifacts in this release have attestations generated with GitHub Artifact Attestations. These can be verified by using the [GitHub CLI](https://cli.github.com/manual/gh_attestation_verify):\n```sh\ngh attestation verify <file-path of downloaded artifact> --repo urin/moove\n```\n\nYou can also download the attestation from [GitHub](https://github.com/urin/moove/attestations) and verify against that directly:\n```sh\ngh attestation verify <file-path of downloaded artifact> --bundle <file-path of downloaded attestation>\n```\n\n",
  "releases": [
    {
      "app_name": "moove",
      "app_version": "0.4.5",
      "env": {
        "install_dir_env_var": "MOOVE_INSTALL_DIR",
        "unmanaged_dir_env_var": "MOOVE_UNMANAGED_INSTALL",
        "disable_update_env_var": "MOOVE_DISABLE_UPDATE",
        "no_modify_path_env_var": "MOOVE_NO_MODIFY_PATH",
        "print_quiet_env_var": "MOOVE_PRINT_QUIET",
        "print_verbose_env_var": "MOOVE_PRINT_VERBOSE",
        "download_url_env_var": "MOOVE_DOWNLOAD_URL",
        "github_base_url_env_var": "MOOVE_INSTALLER_GITHUB_BASE_URL",
        "ghe_base_url_env_var": "MOOVE_INSTALLER_GHE_BASE_URL",
        "github_token_env_var": "MOOVE_GITHUB_TOKEN"
      },
      "display_name": "moove",
      "display": true,
      "artifacts": [
        "moove.rb",
        "sha256.sum",
        "moove-aarch64-apple-darwin.tar.gz",
        "moove-aarch64-apple-darwin.tar.gz.sha256",
        "moove-aarch64-unknown-linux-musl.tar.gz",
        "moove-aarch64-unknown-linux-musl.tar.gz.sha256",
        "moove-x86_64-pc-windows-msvc.zip",
        "moove-x86_64-pc-windows-msvc.zip.sha256",
        "moove-x86_64-unknown-linux-musl.tar.gz",
        "moove-x86_64-unknown-linux-musl.tar.gz.sha256"
      ],
      "hosting": {
        "github": {
          "artifact_base_url": "https://github.com",
          "artifact_download_path": "/urin/moove/releases/download/v0.4.5",
          "owner": "urin",
          "repo": "moove"
        }
      }
    }
  ],
  "artifacts": {
    "moove-aarch64-apple-darwin.tar.gz": {
      "name": "moove-aarch64-apple-darwin.tar.gz",
      "kind": "executable-zip",
      "target_triples": [
        "aarch64-apple-darwin"
      ],
      "assets": [
        {
          "name": "LICENSE-APACHE",
          "path": "LICENSE-APACHE",
          "kind": "license"
        },
        {
          "name": "LICENSE-MIT",
          "path": "LICENSE-MIT",
          "kind": "license"
        },
        {
          "name": "README.md",
          "path": "README.md",
          "kind": "readme"
        },
        {
          "id": "moove-aarch64-apple-darwin-exe-moove",
          "name": "moove",
          "path": "moove",
          "kind": "executable"
        }
      ],
      "checksum": "moove-aarch64-apple-darwin.tar.gz.sha256"
    },
    "moove-aarch64-apple-darwin.tar.gz.sha256": {
      "name": "moove-aarch64-apple-darwin.tar.gz.sha256",
      "kind": "checksum",
      "target_triples": [
        "aarch64-apple-darwin"
      ]
    },
    "moove-aarch64-unknown-linux-musl.tar.gz": {
      "name": "moove-aarch64-unknown-linux-musl.tar.gz",
      "kind": "executable-zip",
      "target_triples": [
        "aarch64-unknown-linux-musl"
      ],
      "assets": [
        {
          "name": "LICENSE-APACHE",
          "path": "LICENSE-APACHE",
          "kind": "license"
        },
        {
          "name": "LICENSE-MIT",
          "path": "LICENSE-MIT",
          "kind": "license"
        },
        {
          "name": "README.md",
          "path": "README.md",
          "kind": "readme"
        },
        {
          "id": "moove-aarch64-unknown-linux-musl-exe-moove",
          "name": "moove",
          "path": "moove",
          "kind": "executable"
        }
      ],
      "checksum": "moove-aarch64-unknown-linux-musl.tar.gz.sha256",
      "checksums": {
        "sha256": "ec092f0b25dbccaed5f4dd39015441d8c19a789bac9213eaf3b43eb3551a91c2"
      }
    },
    "moove-aarch64-unknown-linux-musl.tar.gz.sha256": {
      "name": "moove-aarch64-unknown-linux-musl.tar.gz.sha256",
      "kind": "checksum",
      "target_triples": [
        "aarch64-unknown-linux-musl"
      ]
    },
    "moove-x86_64-pc-windows-msvc.zip": {
      "name": "moove-x86_64-pc-windows-msvc.zip",
      "kind": "executable-zip",
      "target_triples": [
        "x86_64-pc-windows-msvc"
      ],
      "assets": [
        {
          "name": "LICENSE-APACHE",
          "path": "LICENSE-APACHE",
          "kind": "license"
        },
        {
          "name": "LICENSE-MIT",
          "path": "LICENSE-MIT",
          "kind": "license"
        },
        {
          "name": "README.md",
          "path": "README.md",
          "kind": "readme"
        },
        {
          "id": "moove-x86_64-pc-windows-msvc-exe-moove",
          "name": "moove",
          "path": "moove.exe",
          "kind": "executable"
        }
      ],
      "checksum": "moove-x86_64-pc-windows-msvc.zip.sha256"
    },
    "moove-x86_64-pc-windows-msvc.zip.sha256": {
      "name": "moove-x86_64-pc-windows-msvc.zip.sha256",
      "kind": "checksum",
      "target_triples": [
        "x86_64-pc-windows-msvc"
      ]
    },
    "moove-x86_64-unknown-linux-musl.tar.gz": {
      "name": "moove-x86_64-unknown-linux-musl.tar.gz",
      "kind": "executable-zip",
      "target_triples": [
        "x86_64-unknown-linux-musl"
      ],
      "assets": [
        {
          "name": "LICENSE-APACHE",
          "path": "LICENSE-APACHE",
          "kind": "license"
        },
        {
          "name": "LICENSE-MIT",
          "path": "LICENSE-MIT",
          "kind": "license"
        },
        {
          "name": "README.md",
          "path": "README.md",
          "kind": "readme"
        },
        {
          "id": "moove-x86_64-unknown-linux-musl-exe-moove",
          "name": "moove",
          "path": "moove",
          "kind": "executable"
        }
      ],
      "checksum": "moove-x86_64-unknown-linux-musl.tar.gz.sha256"
    },
    "moove-x86_64-unknown-linux-musl.tar.gz.sha256": {
      "name": "moove-x86_64-unknown-linux-musl.tar.gz.sha256",
      "kind": "checksum",
      "target_triples": [
        "x86_64-unknown-linux-musl"
      ]
    },
    "moove.rb": {
      "name": "moove.rb",
      "kind": "installer",
      "target_triples": [
        "aarch64-apple-darwin",
        "aarch64-unknown-linux-gnu",
        "aarch64-unknown-linux-musl-dynamic",
        "aarch64-unknown-linux-musl-static",
        "x86_64-pc-windows-gnu",
        "x86_64-unknown-linux-gnu",
        "x86_64-unknown-linux-musl-dynamic",
        "x86_64-unknown-linux-musl-static"
      ],
      "install_hint": "brew install urin/moove/moove",
      "description": "Install prebuilt binaries via Homebrew"
    },
    "sha256.sum": {
      "name": "sha256.sum",
      "kind": "unified-checksum"
    }
  },
  "systems": {
    "build:local:aarch64-unknown-linux-musl": {
      "id": "build:local:aarch64-unknown-linux-musl",
      "cargo_version_line": "cargo 1.93.1 (083ac5135 2025-12-15)",
      "build_environment": {
        "linux": {
          "glibc_version": {
            "major": 2,
            "series": 35
          }
        }
      }
    },
    "host:create:all:": {
      "id": "host:create:all:",
      "cargo_version_line": "cargo 1.94.1 (29ea6fb6a 2026-03-24)",
      "build_environment": {
        "linux": {
          "glibc_version": {
            "major": 2,
            "series": 35
          }
        }
      }
    }
  },
  "assets": {
    "moove-aarch64-unknown-linux-musl-exe-moove": {
      "id": "moove-aarch64-unknown-linux-musl-exe-moove",
      "name": "moove",
      "system": "build:local:aarch64-unknown-linux-musl",
      "target_triples": [
        "aarch64-unknown-linux-musl"
      ],
      "linkage": {}
    }
  },
  "publish_prereleases": false,
  "force_latest": false,
  "ci": {
    "github": {
      "artifacts_matrix": {
        "include": [
          {
            "runner": "ubuntu-22.04-arm",
            "host": "aarch64-unknown-linux-gnu",
            "install_dist": {
              "shell": "sh",
              "run": "curl --proto '=https' --tlsv1.2 -LsSf https://github.com/axodotdev/cargo-dist/releases/download/v0.31.0/cargo-dist-installer.sh | sh"
            },
            "dist_args": "--artifacts=local --target=aarch64-unknown-linux-musl",
            "targets": [
              "aarch64-unknown-linux-musl"
            ],
            "packages_install": "sudo apt-get update\nsudo apt-get install musl-tools",
            "cache_provider": "github"
          }
        ]
      },
      "pr_run_mode": "plan"
    }
  },
  "linkage": [],
  "upload_files": [
    "/home/runner/work/moove/moove/target/distrib/moove-aarch64-unknown-linux-musl.tar.gz",
    "/home/runner/work/moove/moove/target/distrib/moove-aarch64-unknown-linux-musl.tar.gz.sha256"
  ],
  "github_attestations": true,
  "github_attestations_filters": [
    "*.zip",
    "*.tar.gz"
  ],
  "github_attestations_phase": "host"
}
